dcd_mapping/__init__.py
dcd_mapping/align.py
dcd_mapping/annotate.py
dcd_mapping/cli.py
dcd_mapping/lookup.py
dcd_mapping/main.py
dcd_mapping/mavedb_data.py
dcd_mapping/resource_utils.py
dcd_mapping/schemas.py
dcd_mapping/transcripts.py
dcd_mapping/vrs_map.py
dcd_mapping-0.3.0.dist-info/LICENSE
dcd_mapping-0.3.0.dist-info/METADATA
dcd_mapping-0.3.0.dist-info/WHEEL
dcd_mapping-0.3.0.dist-info/entry_points.txt
dcd_mapping-0.3.0.dist-info/top_level.txt
dcd_mapping-0.3.0.dist-info/RECORD
