Metadata-Version: 2.2
Name: dcd-mapping
Version: 0.3.0
Summary: Map MaveDB scoresets to VRS objects
Author-email: Jeremy Arbesfeld <Jeremy.Arbesfeld@nationwidechildrens.org>, James Stevenson <James.Stevenson@nationwidechildrens.org>, Alan Rubin <alan.rubin@wehi.edu.au>, Alex Handler Wagner <Alex.Wagner@nationwidechildrens.org>
License: MIT License
Project-URL: Homepage, https://www.varianteffect.org/
Project-URL: Documentation, https://github.com/ave-dcd/dcd_mapping/README.md
Project-URL: Source, https://github.com/ave-dcd/dcd_mapping
Classifier: Development Status :: 3 - Alpha
Classifier: Framework :: Pydantic
Classifier: Framework :: Pydantic :: 2
Classifier: License :: OSI Approved :: MIT License
Classifier: Programming Language :: Python
Classifier: Programming Language :: Python :: 3
Classifier: Programming Language :: Python :: 3 :: Only
Classifier: Programming Language :: Python :: 3.10
Classifier: Programming Language :: Python :: 3.11
Classifier: Programming Language :: Python :: 3.12
Classifier: Intended Audience :: Science/Research
Classifier: Topic :: Scientific/Engineering :: Bio-Informatics
Requires-Python: >=3.10
License-File: LICENSE
Requires-Dist: requests
Requires-Dist: biopython
Requires-Dist: tqdm
Requires-Dist: click
Requires-Dist: cool-seq-tool~=0.6.0
Requires-Dist: ga4gh.vrs==2.0.0-a10
Requires-Dist: gene-normalizer[pg]~=0.4.1
Requires-Dist: pydantic~=2.0
Requires-Dist: python-dotenv
Requires-Dist: setuptools>=68.0
Requires-Dist: canonicaljson
Provides-Extra: tests
Requires-Dist: pytest; extra == "tests"
Requires-Dist: pytest-mock; extra == "tests"
Requires-Dist: pytest-cov; extra == "tests"
Requires-Dist: pytest-asyncio; extra == "tests"
Requires-Dist: requests-mock; extra == "tests"
Provides-Extra: dev
Requires-Dist: ruff==0.5.0; extra == "dev"
Requires-Dist: pre-commit>=3.7.1; extra == "dev"
